ellar_storage/__init__.py
ellar_storage/constants.py
ellar_storage/controller.py
ellar_storage/exceptions.py
ellar_storage/module.py
ellar_storage/providers.py
ellar_storage/py.typed
ellar_storage/schemas.py
ellar_storage/services.py
ellar_storage/storage.py
ellar_storage/stored_file.py
ellar_storage/utils.py
ellar_storage-0.1.8.dist-info/licenses/LICENSE
ellar_storage-0.1.8.dist-info/WHEEL
ellar_storage-0.1.8.dist-info/METADATA
ellar_storage-0.1.8.dist-info/RECORD
