Metadata-Version: 2.4
Name: ellar-storage
Version: 0.1.8
Summary: Storage Module for Ellar
Author-email: Ezeudoh Tochukwu <tochukwu.ezeudoh@gmail.com>
Requires-Python: >=3.8
Classifier: Intended Audience :: Information Technology
Classifier: Intended Audience :: System Administrators
Classifier: Operating System :: OS Independent
Classifier: Topic :: Internet
Classifier: Topic :: Software Development :: Libraries :: Application Frameworks
Classifier: Topic :: Software Development :: Libraries :: Python Modules
Classifier: Topic :: Software Development :: Libraries
Classifier: Topic :: Software Development
Classifier: Typing :: Typed
Classifier: Environment :: Web Environment
Classifier: Intended Audience :: Developers
Classifier: License :: OSI Approved :: MIT License
Classifier: Programming Language :: Python :: 3
Classifier: Programming Language :: Python :: 3.8
Classifier: Programming Language :: Python :: 3.9
Classifier: Programming Language :: Python :: 3.10
Classifier: Programming Language :: Python :: 3.11
Classifier: Programming Language :: Python :: 3 :: Only
Classifier: Framework :: AsyncIO
Classifier: Topic :: Internet :: WWW/HTTP :: HTTP Servers
Classifier: Topic :: Internet :: WWW/HTTP
License-File: LICENSE
Requires-Dist: ellar >= 0.8.2
Requires-Dist: apache-libcloud >=3.6, <3.9
Requires-Dist: fasteners ==0.19
Requires-Dist: cryptography>=3.3.1 ; extra == "crypto"
Project-URL: Documentation, https://github.com/python-ellar/ellar-storage
Project-URL: Homepage, https://python-ellar.github.io/ellar-storage/
Project-URL: Source, https://github.com/python-ellar/ellar-storage
Provides-Extra: crypto
